nonebot_plugin_gpt3/__init__.py
nonebot_plugin_gpt3/config.py
nonebot_plugin_gpt3/openai.py
nonebot_plugin_gpt3-1.1.9.dist-info/WHEEL
nonebot_plugin_gpt3-1.1.9.dist-info/METADATA
nonebot_plugin_gpt3-1.1.9.dist-info/RECORD
