Metadata-Version: 2.1
Name: nonebot-plugin-gpt3
Version: 1.1.9
Summary: 
Author: chrisyy
Author-email: 1017975501@qq.com
Requires-Python: >=3.8,<4.0
Classifier: Programming Language :: Python :: 3
Classifier: Programming Language :: Python :: 3.8
Classifier: Programming Language :: Python :: 3.9
Classifier: Programming Language :: Python :: 3.10
Classifier: Programming Language :: Python :: 3.11
Requires-Dist: httpx (>=0.23.1,<0.24.0)
Requires-Dist: nonebot-adapter-onebot (>=2.1.5,<3.0.0)
Requires-Dist: nonebot-plugin-htmlrender (>=0.2.0.3,<0.3.0.0)
Requires-Dist: nonebot2 (>=2.0.0rc2,<3.0.0)
Requires-Dist: tiktoken (==0.3.0)
